circles/__init__.py
circles/admin.py
circles/apps.py
circles/models.py
circles/tests.py
circles/urls.py
circles/utils.py
circles/views.py
circles/migrations/__init__.py
django_circles-0.1.0.dist-info/LICENSE
django_circles-0.1.0.dist-info/METADATA
django_circles-0.1.0.dist-info/WHEEL
django_circles-0.1.0.dist-info/top_level.txt
django_circles-0.1.0.dist-info/RECORD
